_aiofiles_core.cpython-311-x86_64-linux-gnu.so
aiofiles_x-1.0.4.dist-info/WHEEL
aiofiles_x-1.0.4.dist-info/top_level.txt
aiofiles_x-1.0.4.dist-info/METADATA
aiofiles_x-1.0.4.dist-info/RECORD
aiofiles_x-1.0.4.dist-info/licenses/LICENSE
aiofiles/tempfile.py
aiofiles/os.py
aiofiles/threadpool.py
aiofiles/__init__.py
aiofiles/base.py
