Metadata-Version: 2.4
Name: aiofiles-x
Version: 1.0.4
Summary: High-performance async file I/O for Python (C++23 backend)
Author-email: ohmyarthur <ohmyarthur@users.noreply.github.com>
License-Expression: AGPL-3.0-or-later
Project-URL: Homepage, https://github.com/ohmyarthur/aiofiles-x
Project-URL: Documentation, https://github.com/ohmyarthur/aiofiles-x#readme
Project-URL: Repository, https://github.com/ohmyarthur/aiofiles-x
Project-URL: Issues, https://github.com/ohmyarthur/aiofiles-x/issues
Keywords: async,asyncio,file,io,aiofiles,performance
Classifier: Development Status :: 4 - Beta
Classifier: Intended Audience :: Developers
Classifier: Programming Language :: Python :: 3
Classifier: Programming Language :: Python :: 3.10
Classifier: Programming Language :: Python :: 3.11
Classifier: Programming Language :: Python :: 3.12
Classifier: Programming Language :: Python :: 3.13
Classifier: Programming Language :: C++
Classifier: Topic :: Software Development :: Libraries :: Python Modules
Classifier: Topic :: System :: Filesystems
Classifier: Framework :: AsyncIO
Requires-Python: >=3.10
License-File: LICENSE
Provides-Extra: dev
Requires-Dist: pytest>=7.0; extra == "dev"
Requires-Dist: pytest-asyncio>=0.21.0; extra == "dev"
Requires-Dist: pytest-benchmark>=4.0.0; extra == "dev"
Requires-Dist: pytest-cov>=4.0.0; extra == "dev"
Requires-Dist: pytest-timeout>=2.2.0; extra == "dev"
Requires-Dist: black>=23.0; extra == "dev"
Requires-Dist: mypy>=1.0; extra == "dev"
Requires-Dist: ruff>=0.1.0; extra == "dev"
Requires-Dist: pre-commit>=3.0.0; extra == "dev"
Requires-Dist: detect-secrets>=1.4.0; extra == "dev"
Dynamic: license-file
